{
    "LocationEntity": [
        {
            "id": "87a80792-a75b-559b-a6a4-390e2b08e7f1",
            "calendar_id": "c71f5c9e-7a3d-4e5f-8e1a-66c3612a05f3",
            "name": "Washington Park",
            "address": "4033 SW Canyon Rd",
            "city": "Portland",
            "state": "OR",
            "postal_code": "97221",
            "country": "USA"
        },
        {
            "id": "ccbd9e3f-1e5e-54cd-8c1e-30fb3012b26f",
            "calendar_id": "c71f5c9e-7a3d-4e5f-8e1a-66c3612a05f3",
            "name": "Multnomah County Library",
            "address": "801 SW 10th Ave",
            "city": "Portland",
            "state": "OR",
            "postal_code": "97205",
            "country": "USA"
        },
        {
            "id": "3ee7d8f9-0523-5b89-bb12-1279e50d8157",
            "calendar_id": "c71f5c9e-7a3d-4e5f-8e1a-66c3612a05f3",
            "name": "Laurelhurst Park",
            "address": "SE Cesar E Chavez Blvd & Stark St",
            "city": "Portland",
            "state": "OR",
            "postal_code": "97214",
            "country": "USA"
        },
        {
            "id": "665b369a-81c3-5f61-a9ce-df4cc87bb1f6",
            "calendar_id": "ca17e000-6e87-4d89-aa9d-5ef437fe3333",
            "name": "Community Recreation Center",
            "address": "123 Main Street",
            "city": "Portland",
            "state": "OR",
            "postal_code": "97203",
            "country": "USA"
        },
        {
            "id": "56d62d17-5418-5dd1-a9ba-2368310723a0",
            "calendar_id": "ca17e000-6e87-4d89-aa9d-5ef437fe3333",
            "name": "Central Park",
            "address": "456 Oak Avenue",
            "city": "Portland",
            "state": "OR",
            "postal_code": "97204",
            "country": "USA"
        },
        {
            "id": "36471dc0-de8d-5cea-be7e-99709e9707a2",
            "calendar_id": "ca17e000-6e87-4d89-aa9d-5ef437fe4444",
            "name": "Downtown Convention Center",
            "address": "789 Broadway",
            "city": "Portland",
            "state": "OR",
            "postal_code": "97201",
            "country": "USA"
        },
        {
            "id": "30b18244-766f-5b37-ba37-160ab201e32d",
            "calendar_id": "ca17e000-6e87-4d89-aa9d-5ef437fe4444",
            "name": "Riverside Amphitheater",
            "address": "321 River Road",
            "city": "Portland",
            "state": "OR",
            "postal_code": "97202",
            "country": "USA"
        }
    ]
}
